simstock/.DS_Store
simstock/__init__.py
simstock/_algs/__init__.py
simstock/_algs/_coords_algs.py
simstock/_algs/_idf_algs.py
simstock/_algs/_polygon_algs.py
simstock/_algs/_simplification.py
simstock/_utils/.DS_Store
simstock/_utils/__init__.py
simstock/_utils/_dirmanager.py
simstock/_utils/_exceptions.py
simstock/_utils/_serialisation.py
simstock/base.py
simstock/io.py
simstock/plotting.py
simstock/settings/.DS_Store
simstock/settings/DB-Fabric-CONSTRUCTION.csv
simstock/settings/DB-Fabric-MATERIAL.csv
simstock/settings/DB-Fabric-MATERIAL_NOMASS.csv
simstock/settings/DB-Fabric-WINDOWMATERIAL_GAS.csv
simstock/settings/DB-Fabric-WINDOWMATERIAL_GLAZING.csv
simstock/settings/DB-HeatingCooling-OnOff.csv
simstock/settings/DB-Loads-ELECTRICEQUIPMENT.csv
simstock/settings/DB-Loads-LIGHTS.csv
simstock/settings/DB-Loads-PEOPLE.csv
simstock/settings/DB-Schedules-SCHEDULE_COMPACT.csv
simstock/settings/GBR_ENG_London.Wea.Ctr-St.James.Park.037700_TMYx.2007-2021.epw
simstock/settings/base.idf
simstock/settings/infiltration_dict.json
simstock/settings/settings.idf
simstock/settings/ventilation_dict.json
simstock-0.2.4.dist-info/LICENSE
simstock-0.2.4.dist-info/METADATA
simstock-0.2.4.dist-info/WHEEL
simstock-0.2.4.dist-info/RECORD
