Metadata-Version: 2.1
Name: simstock
Version: 0.2.4
Summary: A Python package for building stock simulations
Author: Olly Smith
Author-email: olly.smith@ucl.ac.uk
Requires-Python: >=3.8,<4.0
Classifier: Programming Language :: Python :: 3
Classifier: Programming Language :: Python :: 3.8
Classifier: Programming Language :: Python :: 3.9
Classifier: Programming Language :: Python :: 3.10
Classifier: Programming Language :: Python :: 3.11
Requires-Dist: eppy (>=0.5.63,<0.6.0)
Requires-Dist: fastparquet (>=2023.2.0,<2024.0.0)
Requires-Dist: geopandas (>=0.13.2,<0.14.0)
Requires-Dist: matplotlib (>=3.7.1,<4.0.0)
Requires-Dist: numpy (>=1.24.2,<2.0.0)
Requires-Dist: pandas (>=1.5.3,<2.0.0)
Requires-Dist: shapely (>=2.0.1,<3.0.0)
